sc_oa/__init__.py
sc_oa/sc_oa.py
sc_common_oa-0.0.1.dist-info/METADATA
sc_common_oa-0.0.1.dist-info/WHEEL
sc_common_oa-0.0.1.dist-info/top_level.txt
sc_common_oa-0.0.1.dist-info/RECORD
