Metadata-Version: 2.1
Name: sc-common-oa
Version: 0.0.1
Summary: SC OA 接口修改信息
Home-page: UNKNOWN
Author: river
License: UNKNOWN
Platform: UNKNOWN
Requires-Dist: requests (>=2.0.0)
Requires-Dist: jsonpath (>=0.82)
